airo_teleop/__init__.py
airo_teleop/explore_pygame_game_controller_mapping.py
airo_teleop/game_controller_mapping.py
airo_teleop/game_controller_teleop.py
airo_teleop/py.typed
airo_teleop-2025.8.0.dist-info/METADATA
airo_teleop-2025.8.0.dist-info/WHEEL
airo_teleop-2025.8.0.dist-info/top_level.txt
airo_teleop-2025.8.0.dist-info/RECORD
